torustrateinterface/__init__.py
torustrateinterface/base.py
torustrateinterface/constants.py
torustrateinterface/contracts.py
torustrateinterface/exceptions.py
torustrateinterface/extensions.py
torustrateinterface/interfaces.py
torustrateinterface/key.py
torustrateinterface/keypair.py
torustrateinterface/py.typed
torustrateinterface/storage.py
torustrateinterface/utils/__init__.py
torustrateinterface/utils/caching.py
torustrateinterface/utils/ecdsa_helpers.py
torustrateinterface/utils/encrypted_json.py
torustrateinterface/utils/hasher.py
torustrateinterface/utils/ss58.py
torustrateinterface-0.1.3.dist-info/LICENSE
torustrateinterface-0.1.3.dist-info/METADATA
torustrateinterface-0.1.3.dist-info/WHEEL
torustrateinterface-0.1.3.dist-info/RECORD
