Metadata-Version: 2.1
Name: torustrateinterface
Version: 0.1.3
Summary: substrate-interface fork
Author: PsicoThePato
Author-email: jmomcontato@gmail.com
Requires-Python: >=3.10,<4.0
Classifier: Programming Language :: Python :: 3
Classifier: Programming Language :: Python :: 3.10
Classifier: Programming Language :: Python :: 3.11
Classifier: Programming Language :: Python :: 3.12
Requires-Dist: PyNaCl (>=1.0.1,<2.0.0)
Requires-Dist: certifi (>=2019.3.9,<2020.0.0)
Requires-Dist: ecdsa (>=0.17.0,<0.18.0)
Requires-Dist: eth-keys (>=0.2.1,<0.3.0)
Requires-Dist: eth-utils (>=1.3.0,<2.0.0)
Requires-Dist: idna (>=2.1.0,<3.0.0)
Requires-Dist: py-bip39-bindings (>=0.1.9,<0.2.0)
Requires-Dist: py-ed25519-zebra-bindings (>=1.0,<2.0)
Requires-Dist: py-sr25519-bindings (>=0.2.0,<0.3.0)
Requires-Dist: pycryptodome (>=3.11.0,<4.0.0)
Requires-Dist: requests (>=2.21.0,<3.0.0)
Requires-Dist: scalecodec (>=1.2.7,<2.0.0)
Requires-Dist: setuptools (>=75.0.0,<76.0.0)
Requires-Dist: websocket-client (>=0.57.0,<0.58.0)
Requires-Dist: xxhash (>=1.3.0,<2.0.0)
